alu.v
module alu #(parameter WIDTH = 8)(
    input  wire [WIDTH-1:0] A,        // Первый операнд
    input  wire [WIDTH-1:0] B,        // Второй операнд
    input  wire [3:0] op_code,        // Код операции
    output reg  [WIDTH-1:0] result,   // Результат операции
    output reg  zero,                 // Флаг нуля
    output reg  negative,             // Флаг отрицательного результата
    output reg  carry,                // Флаг переноса
    output reg  overflow              // Флаг переполнения
);

    reg [WIDTH:0] tmp_result; // Регистр с дополнительным битом для учёта переноса
    reg signed [WIDTH-1:0] A_signed, B_signed, result_signed;

    always @(*) begin
        // Обнуление флагов и переменных
        carry     = 0;
        overflow  = 0;
        zero      = 0;
        negative  = 0;
        result    = 0;
        tmp_result = 0;

        A_signed = A;
        B_signed = B;

        case(op_code)
            4'b0000: begin // ADD: сложение
                tmp_result = A + B;
                result     = tmp_result[WIDTH-1:0];
                carry      = tmp_result[WIDTH]; // перенос из старшего разряда
                overflow   = (~A[WIDTH-1] & ~B[WIDTH-1] & result[WIDTH-1]) |
                             (A[WIDTH-1] & B[WIDTH-1] & ~result[WIDTH-1]);
            end

            4'b0001: begin // SUB: вычитание
                tmp_result = A - B;
                result     = tmp_result[WIDTH-1:0];
                carry      = A < B; // признак заёма
                overflow   = (A[WIDTH-1] & ~B[WIDTH-1] & ~result[WIDTH-1]) |
                             (~A[WIDTH-1] & B[WIDTH-1] & result[WIDTH-1]);
            end

            4'b0010: begin // AND: побитовое И
                result = A & B;
                carry = 0;
                overflow = 0;
            end

            4'b0011: begin // OR: побитовое ИЛИ
                result = A | B;
                carry = 0;
                overflow = 0;
            end

            4'b0100: begin // XOR: исключающее ИЛИ
                result = A ^ B;
                carry = 0;
                overflow = 0;
            end

            4'b0101: begin // SHL: сдвиг влево
                tmp_result = {A, 1'b0};  // оценка переноса
                result = A << 1;
                carry = A[WIDTH-1];      // старший бит "вылетает"
                overflow = (A[WIDTH-1] != result[WIDTH-1]); // меняется знак
            end

            4'b0110: begin // SHR: сдвиг вправо (логический)
                result = A >> 1;
                carry = A[0];            // младший бит "вылетает"
                overflow = 0;            // логический сдвиг не вызывает переполнения
            end

            4'b0111: begin // MUL: умножение (младшие биты в результат)
                tmp_result = A * B;
                result = tmp_result[WIDTH-1:0];
                carry = tmp_result[WIDTH]; // оценка переполнения как "перенос"
                overflow = tmp_result[WIDTH]; // если старший бит не влез
            end

            default: begin
                result = 0;
                carry = 0;
                overflow = 0;
            end
        endcase

        // Установка флагов результата
        zero     = (result == 0);        // Если результат — ноль
        negative = result[WIDTH-1];      // Если результат отрицательный (старший бит 1)
    end

endmodule

alu_tb.v
`timescale 1ns / 1ps

module alu_tb;

    reg  [7:0] A, B;
    reg  [3:0] op_code;
    wire [7:0] result;
    wire zero, negative, carry, overflow;

    // Подключение ALU
    alu #(8) dut (
        .A(A),
        .B(B),
        .op_code(op_code),
        .result(result),
        .zero(zero),
        .negative(negative),
        .carry(carry),
        .overflow(overflow)
    );

    initial begin
        // Установка файла для вывода изменений сигналов
        $dumpfile("alu_wave.vcd");       // имя файла 
        $dumpvars(0, alu_tb);            // сохранить все сигналы текущего модуля

        // Заголовок и мониторинг
        $display("Time |  A  |  B  | OP  | Result | Z | N | C | O ");
        $monitor("%4dns | %3d | %3d | %2h  | %3d    | %b | %b | %b | %b",
                 $time, A, B, op_code, result, zero, negative, carry, overflow);

        // Тест 1: ADD
        A = 8'd100; B = 8'd55; op_code = 4'b0000; #10;

        // Тест 2: SUB
        A = 8'd30; B = 8'd100; op_code = 4'b0001; #10;

        // Тест 3: AND
        A = 8'b10101010; B = 8'b11001100; op_code = 4'b0010; #10;

        // Тест 4: OR
        A = 8'b10100000; B = 8'b00001111; op_code = 4'b0011; #10;

        // Тест 5: XOR
        A = 8'b11110000; B = 8'b00001111; op_code = 4'b0100; #10;

        // Тест 6: SHL
        A = 8'b10000001; B = 0; op_code = 4'b0101; #10;

        // Тест 7: SHR
        A = 8'b00000011; B = 0; op_code = 4'b0110; #10;

        // Тест 8: MUL
        A = 8'd15; B = 8'd15; op_code = 4'b0111; #10;

        $finish;
    end

endmodule

alu_wave.vcd
$date
	Wed Apr 23 23:16:28 2025
$end
$version
	Icarus Verilog
$end
$timescale
	1ps
$end
$scope module alu_tb $end
$var wire 1 ! zero $end
$var wire 8 " result [7:0] $end
$var wire 1 # overflow $end
$var wire 1 $ negative $end
$var wire 1 % carry $end
$var reg 8 & A [7:0] $end
$var reg 8 ' B [7:0] $end
$var reg 4 ( op_code [3:0] $end
$scope module dut $end
$var wire 8 ) A [7:0] $end
$var wire 8 * B [7:0] $end
$var wire 4 + op_code [3:0] $end
$var reg 8 , A_signed [7:0] $end
$var reg 8 - B_signed [7:0] $end
$var reg 1 % carry $end
$var reg 1 $ negative $end
$var reg 1 # overflow $end
$var reg 8 . result [7:0] $end
$var reg 9 / tmp_result [8:0] $end
$var reg 1 ! zero $end
$upscope $end
$upscope $end
$enddefinitions $end
#0
$dumpvars
b10011011 /
b10011011 .
b110111 -
b1100100 ,
b0 +
b110111 *
b1100100 )
b0 (
b110111 '
b1100100 &
0%
1$
1#
b10011011 "
0!
$end
#10000
1%
b1100100 -
b11110 ,
b110111010 /
b10111010 "
b10111010 .
1$
0#
b1 (
b1 +
b1100100 '
b1100100 *
b11110 &
b11110 )
#20000
b11001100 -
b10101010 ,
b0 /
b10001000 "
b10001000 .
1$
0%
b10 (
b10 +
b11001100 '
b11001100 *
b10101010 &
b10101010 )
#30000
b1111 -
b10100000 ,
b10101111 "
b10101111 .
1$
b11 (
b11 +
b1111 '
b1111 *
b10100000 &
b10100000 )
#40000
b11110000 ,
b11111111 "
b11111111 .
1$
b100 (
b100 +
b11110000 &
b11110000 )
#50000
1#
1%
b100000010 /
b0 -
b10000001 ,
b10 "
b10 .
0$
b101 (
b101 +
b0 '
b0 *
b10000001 &
b10000001 )
#60000
b11 ,
b0 /
b1 "
b1 .
0#
1%
b110 (
b110 +
b11 &
b11 )
#70000
1$
b11100001 /
b1111 -
b1111 ,
b11100001 "
b11100001 .
0%
b111 (
b111 +
b1111 '
b1111 *
b1111 &
b1111 )
